.gitignore
LICENSE
README.md
pyproject.toml
setup.py
.github/workflows/python-publish.yml
src/barecat_mount/__init__.py
src/barecat_mount/_version.py
src/barecat_mount/barecat_mount.py
src/barecat_mount/barecat_mount_cython.pyx
src/barecat_mount/cli.py
src/barecat_mount/sample_mount.py
src/barecat_mount.egg-info/PKG-INFO
src/barecat_mount.egg-info/SOURCES.txt
src/barecat_mount.egg-info/dependency_links.txt
src/barecat_mount.egg-info/entry_points.txt
src/barecat_mount.egg-info/requires.txt
src/barecat_mount.egg-info/top_level.txt