Metadata-Version: 2.4
Name: barecat-mount
Version: 0.1.2
Summary: Mount Barecat archives with FUSE.
Author-email: István Sárándi <istvan.sarandi@gmail.com>
License: MIT License
Keywords: sqlite,storage,archive,random-access,filesystem,fuse,file-indexing
Classifier: Development Status :: 4 - Beta
Classifier: Intended Audience :: Developers
Classifier: Intended Audience :: Science/Research
Classifier: Topic :: Scientific/Engineering :: Information Analysis
Classifier: Topic :: Software Development :: Libraries
Classifier: Topic :: System :: Archiving
Classifier: Topic :: System :: Filesystems
Classifier: License :: OSI Approved :: MIT License
Classifier: Programming Language :: Python
Classifier: Programming Language :: Python :: 3
Classifier: Programming Language :: Cython
Classifier: Operating System :: POSIX :: Linux
Requires-Python: >=3.9
License-File: LICENSE
Requires-Dist: crc32c
Requires-Dist: barecat
Dynamic: license-file
